throttling_toolkit/__about__.py
throttling_toolkit/__init__.py
throttling_toolkit/simple.py
throttling_toolkit-0.0.3.dist-info/METADATA
throttling_toolkit-0.0.3.dist-info/WHEEL
throttling_toolkit-0.0.3.dist-info/licenses/LICENSE
throttling_toolkit-0.0.3.dist-info/RECORD
