Metadata-Version: 2.3
Name: throttling-toolkit
Version: 0.0.3
Summary: Python implementation of throttling resiliency pattern.
Project-URL: Documentation, https://github.com/davidejames/throttling-toolkit#readme
Project-URL: Issues, https://github.com/davidejames/throttling-toolkit/issues
Project-URL: Source, https://github.com/davidejames/throttling-toolkit
Author-email: "David E. James" <david.eugene.james@protonmail.com>
License-Expression: MIT
License-File: LICENSE
Classifier: Development Status :: 4 - Beta
Classifier: Programming Language :: Python
Classifier: Programming Language :: Python :: 3.8
Classifier: Programming Language :: Python :: 3.9
Classifier: Programming Language :: Python :: 3.10
Classifier: Programming Language :: Python :: 3.11
Classifier: Programming Language :: Python :: 3.12
Classifier: Programming Language :: Python :: Implementation :: CPython
Classifier: Programming Language :: Python :: Implementation :: PyPy
Requires-Python: >=3.8
